Legobot/Chatbot.py
Legobot/Lego.py
Legobot/LegoError.py
Legobot/Message.py
Legobot/Utilities.py
Legobot/__init__.py
Legobot/chatbot_schema.yaml
Legobot/Connectors/Discord.py
Legobot/Connectors/IRC.py
Legobot/Connectors/Slack.py
Legobot/Connectors/__init__.py
Legobot/LegoTests/__init__.py
Legobot/LegoTests/test_TestingConnector.py
Legobot/Legos/Help.py
Legobot/Legos/TestingConnector.py
Legobot/Legos/__init__.py
Legobot-1.3.6.dist-info/LICENSE
Legobot-1.3.6.dist-info/METADATA
Legobot-1.3.6.dist-info/WHEEL
Legobot-1.3.6.dist-info/top_level.txt
Legobot-1.3.6.dist-info/RECORD
